gen_invoice/Configuration.py
gen_invoice/DataFileLoader.py
gen_invoice/InvoiceGenerator.py
gen_invoice/Utility.py
gen_invoice/__init__.py
gen_invoice/__main__.py
gen_invoice/cli.py
gen_invoice/defaults/default.css
gen_invoice/defaults/default.html
gen_invoice-0.0.3.dist-info/LICENSE
gen_invoice-0.0.3.dist-info/METADATA
gen_invoice-0.0.3.dist-info/WHEEL
gen_invoice-0.0.3.dist-info/entry_points.txt
gen_invoice-0.0.3.dist-info/top_level.txt
gen_invoice-0.0.3.dist-info/RECORD
